octo_cli/__init__.py
octo_cli/__main__.py
octo_cli/commands/__init__.py
octo_cli/commands/new.py
octo_cli/controllers/__init__.py
octo_cli/controllers/model.py
octo_cli/main.py
octo_cli/schemas/__init__.py
octo_cli/schemas/column.py
octo_cli/schemas/model.py
octo_cli/templates/__init__.py
octo_cli/templates/model.py.j2
octo_cli-0.1.8.dist-info/LICENSE
octo_cli-0.1.8.dist-info/METADATA
octo_cli-0.1.8.dist-info/WHEEL
octo_cli-0.1.8.dist-info/entry_points.txt
octo_cli-0.1.8.dist-info/RECORD
