Metadata-Version: 2.3
Name: octo-cli
Version: 0.1.8
Summary: 
Author: Samuel Bagatelli
Author-email: contato.samuelbagatelli@gmail.com
Requires-Python: >=3.10
Classifier: Programming Language :: Python :: 3
Classifier: Programming Language :: Python :: 3.10
Classifier: Programming Language :: Python :: 3.11
Classifier: Programming Language :: Python :: 3.12
Classifier: Programming Language :: Python :: 3.13
Requires-Dist: jinja2 (>=3.1.6,<4.0.0)
Requires-Dist: pydantic (>=2.11.7,<3.0.0)
Requires-Dist: typer (>=0.16.0,<0.17.0)
